linux_ticker/__init__.py
linux_ticker/linux_ticker.py
linux_ticker-0.0.12.dist-info/LICENSE
linux_ticker-0.0.12.dist-info/METADATA
linux_ticker-0.0.12.dist-info/WHEEL
linux_ticker-0.0.12.dist-info/top_level.txt
linux_ticker-0.0.12.dist-info/RECORD
