Metadata-Version: 2.1
Name: linux-ticker
Version: 0.0.12
Summary: Simple ticker for use on linux platform with max resolution of 1ms
Home-page: https://github.com/ishworgurung/linux-ticker
Author: Ishwor Gurung
Author-email: me@ishworgurung.com
Maintainer: Ishwor Gurung
Maintainer-email: me@ishworgurung.com
License: MIT License
Platform: UNKNOWN
Classifier: Development Status :: 5 - Production/Stable
Classifier: Environment :: Other Environment
Classifier: Intended Audience :: Developers
Classifier: Operating System :: POSIX :: Linux
Classifier: Programming Language :: Python
Classifier: Programming Language :: Python :: 3
Classifier: Programming Language :: Python :: 3.6
Classifier: Programming Language :: Python :: 3.7
Classifier: Programming Language :: Python :: 3.8
Classifier: Topic :: Software Development
Classifier: Topic :: Utilities
Classifier: License :: OSI Approved :: MIT License
Requires-Python: >=3.6
